km_mcp/__init__.py
km_mcp/server.py
km_mcp/km/__init__.py
km_mcp/km/drawio_to_mermaid.py
km_mcp/km/km2md.py
km_mcp/km/minder_parser.py
km_mcp/sso/__init__.py
km_mcp/sso/browser_cookie_reader.py
km_mcp/sso/config.py
km_mcp/sso/cookie_manager.py
km_mcp/sso/meituan_requests.py
km_mcp/sso/sso_manager.py
km_mcp/utils/__init__.py
km_mcp/utils/appkeyutils.py
km_mcp/utils/logger.py
km_mcp-0.1.4.dist-info/METADATA
km_mcp-0.1.4.dist-info/WHEEL
km_mcp-0.1.4.dist-info/entry_points.txt
km_mcp-0.1.4.dist-info/licenses/LICENSE
km_mcp-0.1.4.dist-info/RECORD
