Metadata-Version: 2.4
Name: km-mcp
Version: 0.1.4
Summary: Meituan Knowledge Management MCP Server - A Model Context Protocol server for accessing Meituan internal documents
Project-URL: Homepage, https://github.com/meituan/km-mcp
Project-URL: Repository, https://github.com/meituan/km-mcp
Project-URL: Documentation, https://github.com/meituan/km-mcp#readme
Project-URL: Bug Tracker, https://github.com/meituan/km-mcp/issues
Author-email: Meituan Engineering Team <engineering@meituan.com>
License: MIT
License-File: LICENSE
Keywords: documentation,knowledge-management,mcp,meituan,wiki
Classifier: Development Status :: 4 - Beta
Classifier: Intended Audience :: Developers
Classifier: License :: OSI Approved :: MIT License
Classifier: Programming Language :: Python :: 3
Classifier: Programming Language :: Python :: 3.10
Classifier: Programming Language :: Python :: 3.11
Classifier: Programming Language :: Python :: 3.12
Classifier: Programming Language :: Python :: 3.13
Classifier: Topic :: Documentation
Classifier: Topic :: Software Development :: Libraries :: Python Modules
Requires-Python: >=3.10
Requires-Dist: beautifulsoup4>=4.13.3
Requires-Dist: browser-cookie3>=0.19.1
Requires-Dist: html2text>=2024.2.26
Requires-Dist: lxml>=4.9.0
Requires-Dist: mcp[cli]>=1.6.0
Requires-Dist: pillow>=10.0.0
Requires-Dist: python-json-logger>=2.0.0
Requires-Dist: requests>=2.31.0
Provides-Extra: dev
Requires-Dist: black>=24.2.0; extra == 'dev'
Requires-Dist: isort>=5.13.0; extra == 'dev'
Requires-Dist: mypy>=1.8.0; extra == 'dev'
Requires-Dist: pytest>=8.0.0; extra == 'dev'
